sigmoid/PLAN/sigmoid.v
/*
 *** Piecewise Linear Approximation ***
 * 
 * fixed_point data precision
 *	[31:0]
 * 		[31]:		sign
 *		[30:24]:	integer
 *		[23:0] :	decimal
 *
 *	[15:0]
 *		[15]:		sign
 *		[14:12]:	integer
 *		[11:0] :	decimal
 */

module sigmoid(clk, rst_n, plan_in, plan_out);
	input wire clk, rst_n;
	input wire [31:0] plan_in;
	output reg [15:0] plan_out;

	reg [31:0] abs_in;
	wire [2:0] sel;

	wire [31:0] abs_lshift_5;
	wire [31:0] abs_lshift_3;
	wire [31:0] abs_lshift_2;
	wire [15:0] in_lshift_5;
	wire [15:0] in_lshift_3;
	wire [15:0] in_lshift_2;

	reg [15:0] add_0, add_1;

assign sel[0] = (abs_in >= 32'h0500_0000) ? 1'b1 : 1'b0;
assign sel[1] = (abs_in >= 32'h0260_0000) ? 1'b1 : 1'b0;
assign sel[2] = (abs_in >= 32'h0100_0000) ? 1'b1 : 1'b0;

assign abs_lshift_5 = abs_in >> 5;
assign abs_lshift_3 = abs_in >> 3;
assign abs_lshift_2 = abs_in >> 2;
assign in_lshift_5 = {1'b0, abs_lshift_5[26:12]};
assign in_lshift_3 = {1'b0, abs_lshift_3[26:12]};
assign in_lshift_2 = {1'b0, abs_lshift_2[26:12]};

always @(plan_in) begin
	// if plan_in is a negative number
	if (plan_in[31]) begin
		/* Exception: 32'h80000000 */
		abs_in = (&(~plan_in[30:0])) ? ~(plan_in+32'h1) + 32'h1 : ~plan_in + 32'h1;
	// if plan_in is a positive number
	end else begin
		abs_in = plan_in;
	end
end

always @(*) begin
	add_0 = 16'h0;
	add_1 = 16'h0;
	case (sel)
		3'b000: begin
			add_0 = 16'h0800;	//Fixed 16'h0800 = 0.5
			add_1 = in_lshift_2;	//abs_in * 0.25
		end
		3'b100: begin
			add_0 = 16'h0a00;	//Fixed 16'h0a00 = 0.625
			add_1 = in_lshift_3;
		end
		3'b110: begin
			add_0 = 16'h0d80;	//Fixed 16'h0d80 = 0.84375
			add_1 = in_lshift_5;
		end
		3'b111: begin
			add_0 = 16'h0;
			add_1 = 16'h1000;
		end
		default: begin
			add_0 = 16'h0;
			add_1 = 16'h1000;
		end
	endcase
end

always @(posedge clk or negedge rst_n) begin
	if (!rst_n) begin
		plan_out <= 16'h0;
	end else begin
		plan_out <= (!plan_in[31]) ? add_0 + add_1 : 16'h1000 - (add_0 + add_1);
	end
end

endmodule

sigmoid/PLAN/test4sigmoid.v
module test;
	reg clk, rst_n;
	reg [31:0] plan_in;
	wire [15:0] plan_out;

parameter STEP = 10;

always #(STEP/2) clk =~ clk;

sigmoid s0(clk, rst_n, plan_in, plan_out);

initial begin
	$dumpfile("test4sigmoid.vcd");
	$dumpvars(0, s0);
	$dumplimit(100000);

	clk <= 0;
	rst_n <= 0;
#STEP
	rst_n <= 1;
#(STEP/2)
	plan_in <= 32'hff_800000;	//-0.5 -> 0.375
#STEP
	plan_in <= 32'h01_400000;	//+1.25 -> 0.78125
#STEP
	plan_in <= 32'h02_800000;	//+2.5 -> 0.921875
#STEP
	plan_in <= 32'hfa_c00000;	//-5.25 -> 0.0
#STEP
	plan_in <= 32'h00_800000;	//+0.5 -> 0.625
#STEP
	plan_in <= 32'hfe_c00000;	//-1.25 -> 0.21875
#STEP
	plan_in <= 32'hfd_800000;	//-2.5 -> 0.078125
#STEP
	plan_in <= 32'h05_400000;	//+5.25 -> 1.0
#STEP
#(STEP*10)
$finish;
end

endmodule

sigmoid/PLAN/test4sigmoid.vcd
$date
	Sat Feb 11 13:29:48 2017
$end
$version
	Icarus Verilog
$end
$timescale
	1s
$end
$scope module test $end
$scope module s0 $end
$var wire 32 ! abs_lshift_2 [31:0] $end
$var wire 32 " abs_lshift_3 [31:0] $end
$var wire 32 # abs_lshift_5 [31:0] $end
$var wire 1 $ clk $end
$var wire 16 % in_lshift_2 [15:0] $end
$var wire 16 & in_lshift_3 [15:0] $end
$var wire 16 ' in_lshift_5 [15:0] $end
$var wire 32 ( plan_in [31:0] $end
$var wire 1 ) rst_n $end
$var wire 3 * sel [2:0] $end
$var reg 32 + abs_in [31:0] $end
$var reg 16 , add_0 [15:0] $end
$var reg 16 - add_1 [15:0] $end
$var reg 16 . plan_out [15:0] $end
$upscope $end
$upscope $end
$enddefinitions $end
#0
$dumpvars
b0 .
b1000000000000 -
b0 ,
bx +
bx *
0)
bx (
b0xxxxxxxxxxxxxxx '
b0xxxxxxxxxxxxxxx &
b0xxxxxxxxxxxxxxx %
0$
b0xxxxxxxxxxxxxxxxxxxxxxxxxxx #
b0xxxxxxxxxxxxxxxxxxxxxxxxxxxxx "
b0xxxxxxxxxxxxxxxxxxxxxxxxxxxxxx !
$end
#5
1$
#10
1)
0$
#15
b100000000000 ,
b1000000000 -
b1000000 '
b100000000 &
b1000000000 %
b0 *
b1000000000000000000 #
b100000000000000000000 "
b1000000000000000000000 !
b100000000000000000000000 +
b0x000000000000 .
b11111111100000000000000000000000 (
1$
#20
0$
#25
b1010000000 -
b101000000000 ,
b10100000 '
b1010000000 &
b10100000000 %
b100 *
b10100000000000000000 #
b1010000000000000000000 "
b10100000000000000000000 !
b1010000000000000000000000 +
b11000000000 .
b1010000000000000000000000 (
1$
#30
0$
#35
b101000000 -
b110110000000 ,
b101000000 '
b10100000000 &
b101000000000 %
b110 *
b101000000000000000000 #
b10100000000000000000000 "
b101000000000000000000000 !
b10100000000000000000000000 +
b110010000000 .
b10100000000000000000000000 (
1$
#40
0$
#45
b1000000000000 -
b0 ,
b1010100000 '
b101010000000 &
b1010100000000 %
b111 *
b1010100000000000000000 #
b101010000000000000000000 "
b1010100000000000000000000 !
b101010000000000000000000000 +
b111011000000 .
b11111010110000000000000000000000 (
1$
#50
0$
#55
b100000000000 ,
b1000000000 -
b1000000 '
b100000000 &
b1000000000 %
b0 *
b1000000000000000000 #
b100000000000000000000 "
b1000000000000000000000 !
b100000000000000000000000 +
b0 .
b100000000000000000000000 (
1$
#60
0$
#65
b1010000000 -
b101000000000 ,
b10100000 '
b1010000000 &
b10100000000 %
b100 *
b10100000000000000000 #
b1010000000000000000000 "
b10100000000000000000000 !
b1010000000000000000000000 +
b101000000000 .
b11111110110000000000000000000000 (
1$
#70
0$
#75
b101000000 -
b110110000000 ,
b101000000 '
b10100000000 &
b101000000000 %
b110 *
b101000000000000000000 #
b10100000000000000000000 "
b101000000000000000000000 !
b10100000000000000000000000 +
b1110000000 .
b11111101100000000000000000000000 (
1$
#80
0$
#85
b1000000000000 -
b0 ,
b1010100000 '
b101010000000 &
b1010100000000 %
b111 *
b1010100000000000000000 #
b101010000000000000000000 "
b1010100000000000000000000 !
b101010000000000000000000000 +
b101000000 .
b101010000000000000000000000 (
1$
#90
0$
#95
b1000000000000 .
1$
