relu/stochastic_rounding/lfsr_relu.v
module relu(clk, rst_n, in, out);
	input wire clk, rst_n;
	/*
	 * [31:31]: sign
	 * [30:24]: decimal
	 * [23:0] : fractional
	 */
	input wire [31:0] in;
	/*
	 * [15:15]: sign
	 * [14:12]: decimal
	 * [11:0] : fractional
	 */
	output reg [15:0] out;

	reg [15:0] lsfr;
	wire [31:0] add;

always @(posedge clk or negedge rst_n) begin
	if (!rst_n) begin
		lsfr <= 16'h9fc7;
		out <= 16'h0;
	end else begin
		lsfr[0] <= lsfr[1];
		lsfr[1] <= lsfr[2];
		lsfr[2] <= lsfr[3];
		lsfr[3] <= lsfr[4];
		lsfr[4] <= lsfr[5];
		lsfr[5] <= lsfr[6];
		lsfr[6] <= lsfr[7];
		lsfr[7] <= lsfr[8];
		lsfr[8] <= lsfr[9];
		lsfr[9] <= lsfr[10];
		lsfr[10] <= lsfr[11];
		lsfr[11] <= lsfr[0] ^ lsfr[12];
		lsfr[12] <= lsfr[13];
		lsfr[13] <= lsfr[0] ^ lsfr[14];
		lsfr[14] <= lsfr[0] ^ lsfr[15];
		lsfr[15] <= lsfr[0];
		if (!add[31]) begin
			out <= (&(!add[30:27])) ? {add[31],add[26:12]} : 16'h7fff;
		end else begin
			out <= 16'h0;
		end
	end
end

assign add = in + {20'h0, lsfr[11:0]};

endmodule

relu/stochastic_rounding/test4relu.v
module test;
	reg clk, rst_n;
	reg [31:0] in;
	wire [15:0] out;

parameter STEP = 10;

always #(STEP/2) clk =~ clk;

relu relu0(clk, rst_n, in, out);

initial begin
	$dumpfile("test4relu.vcd");
	$dumpvars(0, relu0);
	$dumplimit(100000);

	clk <= 0;
	rst_n <= 0;
#STEP
	rst_n <= 1;
#(STEP/2)
	in <= 32'h00_000_800;
#(STEP*30)
$finish;
end

endmodule

relu/stochastic_rounding/test4relu.vcd
$date
	Mon Nov 28 16:26:14 2016
$end
$version
	Icarus Verilog
$end
$timescale
	1s
$end
$scope module test $end
$scope module relu0 $end
$var wire 32 ! add [31:0] $end
$var wire 1 " clk $end
$var wire 32 # in [31:0] $end
$var wire 1 $ rst_n $end
$var reg 16 % lsfr [15:0] $end
$var reg 16 & out [15:0] $end
$upscope $end
$upscope $end
$enddefinitions $end
#0
$dumpvars
b0 &
b1001111111000111 %
0$
bx #
0"
bx !
$end
#5
1"
#10
0"
1$
#15
b1 &
b1010011111100011 %
1"
b100000000000 #
b111111100011 !
#20
0"
#25
b1001111110001 !
b0 &
b1011101111110001 %
1"
#30
0"
#35
b110111111000 !
b1 &
b1011010111111000 %
1"
#40
0"
#45
b1001011111100 !
b0 &
b101101011111100 %
1"
#50
0"
#55
b1010101111110 !
b1 &
b10110101111110 %
1"
#60
0"
#65
b111010111111 !
b1011010111111 %
1"
#70
0"
#75
b101101011111 !
b0 &
b1110001101011111 %
1"
#80
0"
#85
b1000110101111 !
b1001100110101111 %
1"
#90
0"
#95
b110011010111 !
b1 &
b1010010011010111 %
1"
#100
0"
#105
b1001001101011 !
b0 &
b1011101001101011 %
1"
#110
0"
#115
b110100110101 !
b1 &
b1011010100110101 %
1"
#120
0"
#125
b101010011010 !
b0 &
b1011001010011010 %
1"
#130
0"
#135
b1000101001101 !
b101100101001101 %
1"
#140
0"
#145
b110010100110 !
b1 &
b1100010010100110 %
1"
#150
0"
#155
b101001010011 !
b0 &
b110001001010011 %
1"
#160
0"
#165
b1000100101001 !
b1101100100101001 %
1"
#170
0"
#175
b110010010100 !
b1 &
b1000010010010100 %
1"
#180
0"
#185
b101001001010 !
b0 &
b100001001001010 %
1"
#190
0"
#195
b100100100101 !
b10000100100101 %
1"
#200
0"
#205
b1000010010010 !
b1111100010010010 %
1"
#210
0"
#215
b1010001001001 !
b1 &
b111110001001001 %
1"
#220
0"
#225
b111000100100 !
b1101011000100100 %
1"
#230
0"
#235
b1001100010010 !
b0 &
b110101100010010 %
1"
#240
0"
#245
b110110001001 !
b1 &
b11010110001001 %
1"
#250
0"
#255
b101011000100 !
b0 &
b1111001011000100 %
1"
#260
0"
#265
b1000101100010 !
b111100101100010 %
1"
#270
0"
#275
b1010010110001 !
b1 &
b11110010110001 %
1"
#280
0"
#285
b111001011000 !
b1111011001011000 %
1"
#290
0"
#295
b1001100101100 !
b0 &
b111101100101100 %
1"
#300
0"
#305
b1010110010110 !
b1 &
b11110110010110 %
1"
#310
0"
#315
b1011011001011 !
b1111011001011 %
1"
